mltronsSDK/__init__.py
mltronsSDK/api.py
mltrons_sdk-0.4.dist-info/DESCRIPTION.rst
mltrons_sdk-0.4.dist-info/METADATA
mltrons_sdk-0.4.dist-info/RECORD
mltrons_sdk-0.4.dist-info/WHEEL
mltrons_sdk-0.4.dist-info/metadata.json
mltrons_sdk-0.4.dist-info/top_level.txt
