Metadata-Version: 2.0
Name: mltrons-sdk
Version: 0.4
Summary: Automated machine learning platform
Home-page: https://github.com/muz786/mltrons_sdk
Author: Muzammil Sharif
Author-email: muzammil.sharif786@gmail.com
License: Copyright (c) 2018 The Python Packaging Authority
Requires-Dist: requests
